autouam/__init__.py
autouam/__main__.py
autouam/cli/__init__.py
autouam/cli/commands.py
autouam/config/__init__.py
autouam/config/settings.py
autouam/config/validators.py
autouam/core/__init__.py
autouam/core/cloudflare.py
autouam/core/monitor.py
autouam/core/state.py
autouam/core/uam_manager.py
autouam/health/__init__.py
autouam/health/checks.py
autouam/health/server.py
autouam/logging/__init__.py
autouam/logging/setup.py
autouam-1.0.0a9.dist-info/licenses/LICENSE.md
autouam-1.0.0a9.dist-info/METADATA
autouam-1.0.0a9.dist-info/WHEEL
autouam-1.0.0a9.dist-info/entry_points.txt
autouam-1.0.0a9.dist-info/top_level.txt
autouam-1.0.0a9.dist-info/RECORD
